LICENSE
README.md
setup.py
deepposekit/__init__.py
deepposekit/callbacks.py
deepposekit/annotate/KMeansSampler.py
deepposekit/annotate/__init__.py
deepposekit/annotate/utils/__init__.py
deepposekit/annotate/utils/hotkeys.py
deepposekit/annotate/utils/image.py
deepposekit/augment/FlipAxis.py
deepposekit/augment/__init__.py
deepposekit/io/BaseGenerator.py
deepposekit/io/DLCDataGenerator.py
deepposekit/io/DataGenerator.py
deepposekit/io/ImageGenerator.py
deepposekit/io/TrainingGenerator.py
deepposekit/io/__init__.py
deepposekit/io/utils.py
deepposekit/models/DeepLabCut.py
deepposekit/models/LEAP.py
deepposekit/models/StackedDenseNet.py
deepposekit/models/StackedHourglass.py
deepposekit/models/__init__.py
deepposekit/models/engine.py
deepposekit/models/loading.py
deepposekit/models/saving.py
deepposekit/models/backend/__init__.py
deepposekit/models/backend/backend.py
deepposekit/models/backend/registration.py
deepposekit/models/backend/utils.py
deepposekit/models/layers/__init__.py
deepposekit/models/layers/convolutional.py
deepposekit/models/layers/deeplabcut.py
deepposekit/models/layers/densenet.py
deepposekit/models/layers/hourglass.py
deepposekit/models/layers/imagenet_densenet.py
deepposekit/models/layers/imagenet_mobile.py
deepposekit/models/layers/imagenet_resnet.py
deepposekit/models/layers/imagenet_utils.py
deepposekit/models/layers/imagenet_xception.py
deepposekit/models/layers/leap.py
deepposekit/models/layers/squeeze_excitation.py
deepposekit/models/layers/subpixel.py
deepposekit/models/layers/util.py
deepposekit/utils/__init__.py
deepposekit/utils/image.py
deepposekit/utils/io.py
deepposekit/utils/keypoints.py
us2deepposekit.egg-info/PKG-INFO
us2deepposekit.egg-info/SOURCES.txt
us2deepposekit.egg-info/dependency_links.txt
us2deepposekit.egg-info/not-zip-safe
us2deepposekit.egg-info/requires.txt
us2deepposekit.egg-info/top_level.txt