Metadata-Version: 2.1
Name: us2deepposekit
Version: 0.4.0
Summary: a toolkit for pose estimation using deep learning
Home-page: https://github.com/jgraving/deepposekit
Download-URL: https://github.com/jgraving/deepposekit.git
Author: Jacob Graving <jgraving@gmail.com>
Author-email: jgraving@gmail.com
Maintainer: Jacob Graving <jgraving@gmail.com>
Maintainer-email: jgraving@gmail.com
License: Apache 2.0
Classifier: Intended Audience :: Science/Research
Classifier: Programming Language :: Python :: 3
Classifier: Topic :: Scientific/Engineering :: Image Recognition
License-File: LICENSE
